MANIFEST.in
README.rst
setup.py
aoet/__init__.py
aoet.egg-info/PKG-INFO
aoet.egg-info/SOURCES.txt
aoet.egg-info/dependency_links.txt
aoet.egg-info/not-zip-safe
aoet.egg-info/requires.txt
aoet.egg-info/top_level.txt
aoet/analysis/__init__.py
aoet/analysis/analyzer.py
aoet/analysis/clique.py
aoet/analysis/pca.py
aoet/parser/__init__.py
aoet/parser/matrix_parser.py
aoet/proxy/__init__.py
aoet/proxy/http.py
aoet/proxy/splitter.py
aoet/report/__init__.py
aoet/report/generator.py
aoet/report/resources/results.html
bin/aoet