Metadata-Version: 1.0
Name: aoet
Version: 0.8
Summary: Automation of Exploratory Testing
Home-page: https://gitlab.tubit.tu-berlin.de/abar/aoet
Author: Anton Bardishev
Author-email: abar@protonmail.ch
License: MIT
Platform: UNKNOWN
